simetrix/__about__.py
simetrix/__init__.py
simetrix/__init__.pyi
simetrix/dvm.py
simetrix/dvm.pyi
simetrix/script.py
simetrix/script.pyi
simetrix-9.2.2.dist-info/METADATA
simetrix-9.2.2.dist-info/WHEEL
simetrix-9.2.2.dist-info/licenses/LICENSE.txt
simetrix-9.2.2.dist-info/RECORD
