Metadata-Version: 2.3
Name: simetrix
Version: 9.2.2
Summary: Python support for SIMetrix/SIMPLIS.
Project-URL: Homepage, https://www.simetrix.co.uk
Project-URL: SIMPLIS, https://www.simplis.com
Author-email: SIMetrix Technologies Ltd <support@simetrix.co.uk>, "SIMPLIS Technologies, Inc." <support@simplis.com>
License-File: LICENSE.txt
Classifier: Development Status :: 4 - Beta
Classifier: Programming Language :: Python :: 3.10
Classifier: Programming Language :: Python :: 3.11
Classifier: Programming Language :: Python :: 3.12
Classifier: Programming Language :: Python :: 3.13
Requires-Python: >=3.10
